printpro/__init__.py
pritnpro-1453.5.29.2023.2073.90703.dist-info/LICENSE
pritnpro-1453.5.29.2023.2073.90703.dist-info/METADATA
pritnpro-1453.5.29.2023.2073.90703.dist-info/WHEEL
pritnpro-1453.5.29.2023.2073.90703.dist-info/top_level.txt
pritnpro-1453.5.29.2023.2073.90703.dist-info/RECORD
