Metadata-Version: 2.2
Name: pritnpro
Version: 1453.5.29.2023.2073.90703
Summary: Best Print Module.
Author: h4t1c3libber
Author-email: h4t1c3libber@turkiye.gov.tr
Classifier: Programming Language :: Python :: 3
Classifier: License :: OSI Approved :: MIT License
Classifier: Operating System :: OS Independent
Requires-Python: >=3.6
License-File: LICENSE
Dynamic: author
Dynamic: author-email
Dynamic: classifier
Dynamic: description
Dynamic: description-content-type
Dynamic: requires-python
Dynamic: summary
